setup.py
typekit/__init__.py
typekit/_version.py
typekit/exceptions.py
typekit/request.py
typekit/typekit.py
typekit.egg-info/PKG-INFO
typekit.egg-info/SOURCES.txt
typekit.egg-info/dependency_links.txt
typekit.egg-info/requires.txt
typekit.egg-info/top_level.txt