Metadata-Version: 1.1
Name: typekit
Version: 0.0.4
Summary: Python wrapper for Typekit Developer API
Home-page: https://github.com/suchanlee/typekit-python
Author: Suchan Lee
Author-email: lee.suchan@gmail.com
License: MIT
Download-URL: https://github.com/suchanlee/typekit-python/tarball/0.0.4
Keywords: typekit,typekit-python,typekit python
Platform: UNKNOWN
